<annotation>
  <folder>Apple</folder>
  <filename>0125268651daa59c.jpg</filename>
  <path>C:\Users\Neha Shaikh\Documents\OIDv4_ToolKit\OID\Dataset\train\Apple\0125268651daa59c.jpg</path>
  <source>
    <database>Unknown</database>
  </source>
  <size>
    <width>1024</width>
    <height>768</height>
    <depth>3</depth>
  </size>
  <segmented>0</segmented>
  <object>
    <name>Apple</name>
    <pose>Unspecified</pose>
    <truncated>0</truncated>
    <difficult>0</difficult>
    <bndbox>
      <xmin>0</xmin>
      <ymin>208</ymin>
      <xmax>303</xmax>
      <ymax>481</ymax>
    </bndbox>
  </object>
  <object>
    <name>Apple</name>
    <pose>Unspecified</pose>
    <truncated>0</truncated>
    <difficult>0</difficult>
    <bndbox>
      <xmin>126</xmin>
      <ymin>196</ymin>
      <xmax>331</xmax>
      <ymax>292</ymax>
    </bndbox>
  </object>
  <object>
    <name>Apple</name>
    <pose>Unspecified</pose>
    <truncated>0</truncated>
    <difficult>0</difficult>
    <bndbox>
      <xmin>362</xmin>
      <ymin>262</ymin>
      <xmax>757</xmax>
      <ymax>708</ymax>
    </bndbox>
  </object>
</annotation>
