<annotation>
  <folder>Apple</folder>
  <filename>433ca4a17c31e82a.jpg</filename>
  <path>C:\Users\Neha Shaikh\Documents\OIDv4_ToolKit\OID\Dataset\train\Apple\433ca4a17c31e82a.jpg</path>
  <source>
    <database>Unknown</database>
  </source>
  <size>
    <width>1024</width>
    <height>683</height>
    <depth>3</depth>
  </size>
  <segmented>0</segmented>
  <object>
    <name>Apple</name>
    <pose>Unspecified</pose>
    <truncated>0</truncated>
    <difficult>0</difficult>
    <bndbox>
      <xmin>202</xmin>
      <ymin>158</ymin>
      <xmax>647</xmax>
      <ymax>544</ymax>
    </bndbox>
  </object>
</annotation>
