<annotation>
  <folder>Apple</folder>
  <filename>85e719ce25a12acd.jpg</filename>
  <path>C:\Users\Neha Shaikh\Documents\OIDv4_ToolKit\OID\Dataset\train\Apple\85e719ce25a12acd.jpg</path>
  <source>
    <database>Unknown</database>
  </source>
  <size>
    <width>678</width>
    <height>1024</height>
    <depth>3</depth>
  </size>
  <segmented>0</segmented>
  <object>
    <name>Apple</name>
    <pose>Unspecified</pose>
    <truncated>0</truncated>
    <difficult>0</difficult>
    <bndbox>
      <xmin>267</xmin>
      <ymin>700</ymin>
      <xmax>488</xmax>
      <ymax>910</ymax>
    </bndbox>
  </object>
  <object>
    <name>Apple</name>
    <pose>Unspecified</pose>
    <truncated>0</truncated>
    <difficult>0</difficult>
    <bndbox>
      <xmin>112</xmin>
      <ymin>545</ymin>
      <xmax>287</xmax>
      <ymax>738</ymax>
    </bndbox>
  </object>
</annotation>
